SAR_change_detector/SAR_change_detector.py
SAR_change_detector/__init__.py
SAR_change_detector-0.1.3.1.dist-info/LICENCE.txt
SAR_change_detector-0.1.3.1.dist-info/METADATA
SAR_change_detector-0.1.3.1.dist-info/WHEEL
SAR_change_detector-0.1.3.1.dist-info/top_level.txt
SAR_change_detector-0.1.3.1.dist-info/RECORD
