Metadata-Version: 2.1
Name: SAR-change-detector
Version: 0.1.3.1
Summary: A package for detecting changes between two images using Isolation Forest
Home-page: https://github.com/Selimgit/SAR_change_detection
Author: Selim Behloul
Author-email: selim.behloul@gmail.com
License: UNKNOWN
Platform: UNKNOWN
Classifier: Programming Language :: Python :: 3
Classifier: License :: OSI Approved :: GNU Affero General Public License v3
Classifier: Operating System :: OS Independent
Requires-Python: >=3.6
Requires-Dist: numpy
Requires-Dist: scikit-learn
Requires-Dist: scipy
